MANIFEST.in
README.txt
distribute_setup.py
setup.py
filelike/__init__.py
filelike/tests.py
filelike.egg-info/PKG-INFO
filelike.egg-info/SOURCES.txt
filelike.egg-info/dependency_links.txt
filelike.egg-info/top_level.txt
filelike/pipeline/__init__.py
filelike/pipeline/tests.py
filelike/wrappers/__init__.py
filelike/wrappers/buffer.py
filelike/wrappers/compress.py
filelike/wrappers/crypto.py
filelike/wrappers/debug.py
filelike/wrappers/fixedblocksize.py
filelike/wrappers/padtoblocksize.py
filelike/wrappers/slice.py
filelike/wrappers/translate.py
filelike/wrappers/unix.py
filelike/wrappers/tests/__init__.py
filelike/wrappers/tests/test_buffer.py
filelike/wrappers/tests/test_compress.py
filelike/wrappers/tests/test_crypto.py
filelike/wrappers/tests/test_fixedblocksize.py
filelike/wrappers/tests/test_padtoblocksize.py
filelike/wrappers/tests/test_slice.py
filelike/wrappers/tests/test_translate.py
filelike/wrappers/tests/test_unix.py
filelike/wrappers/tests/tests.py