Metadata-Version: 1.0
Name: filelike
Version: 0.4.1
Summary: Classes for creating and wrapping file-like objects
Home-page: http://www.rfk.id.au/software/filelike/
Author: Ryan Kelly
Author-email: ryan@rfk.id.au
License: LGPL
Keywords: file filelike file-like filter crypt compress
Platform: UNKNOWN
